Workbook

Sheet Dashboard
B5: Current Month-> | C5: Mayıs
B6: Figures in USD | C6: Budget | D6: Actual | F6: Var.Abs | G6: Var.%
B7: Income:
B8: Base Salary | C8: =INDEX(Budget!$B$4:$N$18,MATCH(Dashboard!B8,Budget!$B$4:$B$18,0),MATCH(Dashboard!$C$5,Budget!$B$4:$N$4,0)) -> 3000 | D8: =SUMIFS(Actual!F:F,Actual!D:D,Dashboard!B8,Actual!C:C,Dashboard!$C$5) -> 3000 | F8: =D8-C8 -> 0 | G8: =D8/C8-1 -> 0
B9: Bonus | C9: =INDEX(Budget!$B$4:$N$18,MATCH(Dashboard!B9,Budget!$B$4:$B$18,0),MATCH(Dashboard!$C$5,Budget!$B$4:$N$4,0)) -> 500 | D9: =SUMIFS(Actual!F:F,Actual!D:D,Dashboard!B9,Actual!C:C,Dashboard!$C$5) -> 708 | F9: =D9-C9 -> 208 | G9: =D9/C9-1 -> 0.416
B10: Side Hustle | C10: =INDEX(Budget!$B$4:$N$18,MATCH(Dashboard!B10,Budget!$B$4:$B$18,0),MATCH(Dashboard!$C$5,Budget!$B$4:$N$4,0)) -> 285.61 | D10: =SUMIFS(Actual!F:F,Actual!D:D,Dashboard!B10,Actual!C:C,Dashboard!$C$5) -> 366 | F10: =D10-C10 -> 80.39 | G10: =D10/C10-1 -> 0.28146774
B11: Total Income | C11: =SUM(C8:C10) -> 3785.61 | D11: =SUM(D8:D10) -> 4074 | F11: =D11-C11 -> 288.39 | G11: =D11/C11-1 -> 0.076180589
B13: Expenses:
B14: Rent | C14: =INDEX(Budget!$B$4:$N$18,MATCH(Dashboard!B14,Budget!$B$4:$B$18,0),MATCH(Dashboard!$C$5,Budget!$B$4:$N$4,0)) -> 1120 | D14: =SUMIFS(Actual!F:F,Actual!D:D,Dashboard!B14,Actual!C:C,Dashboard!$C$5) -> 1120 | F14: =C14-D14 -> 0 | G14: =C14/D14-1 -> 0
B15: Utilities | C15: =INDEX(Budget!$B$4:$N$18,MATCH(Dashboard!B15,Budget!$B$4:$B$18,0),MATCH(Dashboard!$C$5,Budget!$B$4:$N$4,0)) -> 112 | D15: =SUMIFS(Actual!F:F,Actual!D:D,Dashboard!B15,Actual!C:C,Dashboard!$C$5) -> 155 | F15: =C15-D15 -> -43 | G15: =C15/D15-1 -> -0.27741935
B16: Transport | C16: =INDEX(Budget!$B$4:$N$18,MATCH(Dashboard!B16,Budget!$B$4:$B$18,0),MATCH(Dashboard!$C$5,Budget!$B$4:$N$4,0)) -> 55 | D16: =SUMIFS(Actual!F:F,Actual!D:D,Dashboard!B16,Actual!C:C,Dashboard!$C$5) -> 55 | F16: =C16-D16 -> 0 | G16: =C16/D16-1 -> 0
B17: Groceries | C17: =INDEX(Budget!$B$4:$N$18,MATCH(Dashboard!B17,Budget!$B$4:$B$18,0),MATCH(Dashboard!$C$5,Budget!$B$4:$N$4,0)) -> 550 | D17: =SUMIFS(Actual!F:F,Actual!D:D,Dashboard!B17,Actual!C:C,Dashboard!$C$5) -> 449 | F17: =C17-D17 -> 101 | G17: =C17/D17-1 -> 0.22494432
B18: Leisure | C18: =INDEX(Budget!$B$4:$N$18,MATCH(Dashboard!B18,Budget!$B$4:$B$18,0),MATCH(Dashboard!$C$5,Budget!$B$4:$N$4,0)) -> 400 | D18: =SUMIFS(Actual!F:F,Actual!D:D,Dashboard!B18,Actual!C:C,Dashboard!$C$5) -> 646 | F18: =C18-D18 -> -246 | G18: =C18/D18-1 -> -0.38080495
B19: Other | C19: =INDEX(Budget!$B$4:$N$18,MATCH(Dashboard!B19,Budget!$B$4:$B$18,0),MATCH(Dashboard!$C$5,Budget!$B$4:$N$4,0)) -> 100 | D19: =SUMIFS(Actual!F:F,Actual!D:D,Dashboard!B19,Actual!C:C,Dashboard!$C$5) -> 249 | F19: =C19-D19 -> -149 | G19: =C19/D19-1 -> -0.59839357
B20: Total Expenses | C20: =SUM(C14:C19) -> 2337 | D20: =SUM(D14:D19) -> 2674 | F20: =C20-D20 -> -337 | G20: =C20/D20-1 -> -0.12602842
B22: Savings | C22: =C11-C20 -> 1448.61 | D22: =D11-D20 -> 1400 | F22: =D22-C22 -> -48.61 | G22: =D22/C22-1 -> -0.033556306

Sheet Budget
B2: Budgeted Income & Expenses 2026
B4: Figures in USD | C4: Ocak | D4: Şubat | E4: Mart | F4: Nisan | G4: Mayıs | H4: Haziran | I4: Temmuz | J4: Ağustos | K4: Eylül | L4: Ekim | M4: Kasım | N4: Aralık
B5: Income:
B6: Base Salary | C6: 2200 | D6: 2200 | E6: 2200 | F6: 3000 | G6: 3000 | H6: 3000 | I6: 3000 | J6: 3000 | K6: 3000 | L6: 3000 | M6: 3000 | N6: 3000
B7: Bonus | C7: 500 | D7: =C7*1.1 -> 550 | E7: 500 | F7: 500 | G7: 500 | H7: 500 | I7: 500 | J7: 500 | K7: 500 | L7: 500 | M7: 500 | N7: 500
B8: Side Hustle | C8: 100 | D8: =C8*1.3 -> 130 | E8: =D8*1.3 -> 169 | F8: =E8*1.3 -> 219.7 | G8: =F8*1.3 -> 285.61 | H8: =G8*1.3 -> 371.293 | I8: =H8*1.3 -> 482.6809 | J8: =I8*1.3 -> 627.48517 | K8: =J8*1.3 -> 815.73072 | ... N8: =M8*1.3 -> 1792.1604
B9: Total Income | C9: =SUM(C6:C8) -> 2800 | D9: =SUM(D6:D8) -> 2880 | E9: =SUM(E6:E8) -> 2869 | F9: =SUM(F6:F8) -> 3719.7 | G9: =SUM(G6:G8) -> 3785.61 | H9: =SUM(H6:H8) -> 3871.293 | I9: =SUM(I6:I8) -> 3982.6809 | J9: =SUM(J6:J8) -> 4127.4852 | ... N9: =SUM(N6:N8) -> 5292.1604
B11: Expenses:
B12: Rent | C12: 1120 | D12: 1120 | E12: 1120 | F12: 1120 | G12: 1120 | H12: 1120 | I12: 1120 | J12: 1120 | K12: 1120 | L12: 1120 | M12: 1120 | N12: 1120
B13: Utilities | C13: =C12*0.1 -> 112 | D13: =D12*0.1 -> 112 | E13: =E12*0.1 -> 112 | F13: =F12*0.1 -> 112 | G13: =G12*0.1 -> 112 | H13: =H12*0.1 -> 112 | I13: =I12*0.1 -> 112 | J13: =J12*0.1 -> 112 | ... N13: =N12*0.1 -> 112
B14: Transport | C14: 55 | D14: 55 | E14: 55 | F14: 55 | G14: 55 | H14: 55 | I14: 55 | J14: 55 | K14: 55 | L14: 55 | M14: 55 | N14: 55
B15: Groceries | C15: 550 | D15: 550 | E15: 550 | F15: 550 | G15: 550 | H15: 550 | I15: 550 | J15: 550 | K15: 550 | L15: 550 | M15: 550 | N15: 550
B16: Leisure | C16: 400 | D16: 400 | E16: 400 | F16: 400 | G16: 400 | H16: 400 | I16: 400 | J16: 400 | K16: 400 | L16: 400 | M16: 400 | N16: 400
B17: Other | C17: 100 | D17: 100 | E17: 100 | F17: 100 | G17: 100 | H17: 100 | I17: 100 | J17: 100 | K17: 100 | L17: 100 | M17: 100 | N17: 100
B18: Total Expenses | C18: =SUM(C12:C17) -> 2337 | D18: =SUM(D12:D17) -> 2337 | E18: =SUM(E12:E17) -> 2337 | F18: =SUM(F12:F17) -> 2337 | G18: =SUM(G12:G17) -> 2337 | H18: =SUM(H12:H17) -> 2337 | I18: =SUM(I12:I17) -> 2337 | J18: =SUM(J12:J17) -> 2337 | ... N18: =SUM(N12:N17) -> 2337
B20: Savings | C20: =C9-C18 -> 463 | D20: =D9-D18 -> 543 | E20: =E9-E18 -> 532 | F20: =F9-F18 -> 1382.7 | G20: =G9-G18 -> 1448.61 | H20: =H9-H18 -> 1534.293 | I20: =I9-I18 -> 1645.6809 | J20: =J9-J18 -> 1790.4852 | ... N20: =N9-N18 -> 2955.1604
B21: Cumulative Savings | C21: =C20 -> 463 | D21: =D20+C21 -> 1006 | E21: =E20+D21 -> 1538 | F21: =F20+E21 -> 2920.7 | G21: =G20+F21 -> 4369.31 | H21: =H20+G21 -> 5903.603 | I21: =I20+H21 -> 7549.2839 | J21: =J20+I21 -> 9339.7691 | K21: =K20+J21 -> 11318.5 | ... N21: =N20+M21 -> 19038.695

Sheet Actual
B2: Actual Income & Expenses 2026
B4: Date | C4: Month | D4: Category | E4: Description | F4: Amount | H4: Categories
B5: 46023 | C5: =TEXT(B5,"AAAA") -> Ocak | D5: Rent | E5: Apartment split with friend | F5: 1120 | H5: Base Salary
B6: 46023 | C6: =TEXT(B6,"AAAA") -> Ocak | D6: Utilities | E6: Higher month than usual | F6: 140 | H6: Bonus
B7: 46023 | C7: =TEXT(B7,"AAAA") -> Ocak | D7: Transport | E7: Metro card | F7: 55 | H7: Side Hustle
B8: 46030 | C8: =TEXT(B8,"AAAA") -> Ocak | D8: Groceries | E8: Walmart shopping | F8: 449 | H8: Rent
B9: 46033 | C9: =TEXT(B9,"AAAA") -> Ocak | D9: Leisure | E9: Hotel in NYC | F9: 245 | H9: Utilities
B10: 46034 | C10: =TEXT(B10,"AAAA") -> Ocak | D10: Leisure | E10: Dinner with friends (invited my partner) | F10: 168 | H10: Transport
B11: 46034 | C11: =TEXT(B11,"AAAA") -> Ocak | D11: Leisure | E11: Drake concert | F11: 149 | H11: Groceries
B12: 46036 | C12: =TEXT(B12,"AAAA") -> Ocak | D12: Other | E12: Bought new clothes | F12: 249 | H12: Leisure
B13: 46053 | C13: =TEXT(B13,"AAAA") -> Ocak | D13: Bonus | E13: Commissions from each sale | F13: 458 | H13: Other
B14: 46053 | C14: =TEXT(B14,"AAAA") -> Ocak | D14: Base Salary | E14: 9-5 job | F14: 3000
B15: 46053 | C15: =TEXT(B15,"AAAA") -> Ocak | D15: Side Hustle | E15: Startup idea $ | F15: 184
B16: 46054 | C16: =TEXT(B16,"AAAA") -> Şubat | D16: Rent | E16: Apartment split with friend | F16: 1120
B17: 46054 | C17: =TEXT(B17,"AAAA") -> Şubat | D17: Utilities | E17: Average month | F17: 105
B18: 46054 | C18: =TEXT(B18,"AAAA") -> Şubat | D18: Transport | E18: Metro card | F18: 55
B19: 46061 | C19: =TEXT(B19,"AAAA") -> Şubat | D19: Groceries | E19: Walmart shopping | F19: 305
B20: 46064 | C20: =TEXT(B20,"AAAA") -> Şubat | D20: Leisure | E20: Drinks out | F20: 28
B21: 46065 | C21: =TEXT(B21,"AAAA") -> Şubat | D21: Leisure | E21: Date night | F21: 99
B22: 46065 | C22: =TEXT(B22,"AAAA") -> Şubat | D22: Leisure | E22: Tennis x2 | F22: 67
B23: 46067 | C23: =TEXT(B23,"AAAA") -> Şubat | D23: Other | E23: Snacks | F23: 18
B24: 46081 | C24: =TEXT(B24,"AAAA") -> Şubat | D24: Bonus | E24: Commissions from each sale | F24: 305
B25: 46081 | C25: =TEXT(B25,"AAAA") -> Şubat | D25: Base Salary | E25: 9-5 job | F25: 3000
... B59: 46170 | C59: =TEXT(B59,"AAAA") -> Mayıs | D59: Side Hustle | E59: Startup idea $ | F59: 366
